football_badges/__init__.py
football_badges/__main__.py
football_badges/py.typed
football_badges/template.svg
football_badges/utils.py
football_badges-0.1.0.dist-info/LICENSE
football_badges-0.1.0.dist-info/METADATA
football_badges-0.1.0.dist-info/WHEEL
football_badges-0.1.0.dist-info/top_level.txt
football_badges-0.1.0.dist-info/RECORD
