Metadata-Version: 2.1
Name: football-badges
Version: 0.1.0
Summary: Create a GitHub-style badge showing the score of a football match.
Home-page: https://github.com/domdfcoding/football_badges
Author: Dominic Davis-Foster
Author-email: dominic@davis-foster.co.uk
License: Apache Software License
Project-URL: Documentation, https://football_badges.readthedocs.io/en/latest
Project-URL: Issue Tracker, https://github.com/domdfcoding/football_badges/issues
Project-URL: Source Code, https://github.com/domdfcoding/football_badges
Keywords: github,gh-badges,badge,shield,football,sport
Platform: Windows
Platform: macOS
Platform: Linux
Classifier: Development Status :: 4 - Beta
Classifier: Intended Audience :: Developers
Classifier: License :: OSI Approved :: Apache Software License
Classifier: Operating System :: OS Independent
Classifier: Programming Language :: Python
Classifier: Programming Language :: Python :: 3 :: Only
Classifier: Programming Language :: Python :: 3.6
Classifier: Programming Language :: Python :: 3.7
Classifier: Programming Language :: Python :: 3.8
Classifier: Programming Language :: Python :: 3.9
Classifier: Programming Language :: Python :: Implementation :: CPython
Classifier: Typing :: Typed
Requires-Python: >=3.6.1
Requires-Dist: click (>=7.1.2)
Requires-Dist: consolekit (>=0.6.0)
Requires-Dist: domdf-python-tools (>=1.9.0)
Requires-Dist: jinja2 (>=2.11.2)
Requires-Dist: lxml (>=4.6.2)
Requires-Dist: pybadges (>=2.2.1)
Provides-Extra: all
Requires-Dist: Pillow (<6,>=5) ; extra == 'all'
Provides-Extra: pil-measurement
Requires-Dist: Pillow (<6,>=5) ; extra == 'pil-measurement'
